README.md
setup.py
fetool/__init__.py
fetool/benchmark.py
fetool/check_skew.py
fetool/csv_to_parquet.py
fetool/fetool.py
fetool/gen_fedb_ddl.py
fetool/inspect_parquet.py
fetool/run_yaml.py
fetool/sample_parquet.py
fetool/version.py
fetool.egg-info/PKG-INFO
fetool.egg-info/SOURCES.txt
fetool.egg-info/dependency_links.txt
fetool.egg-info/entry_points.txt
fetool.egg-info/not-zip-safe
fetool.egg-info/requires.txt
fetool.egg-info/top_level.txt