Metadata-Version: 2.1
Name: fetool
Version: 0.1.3
Summary: The featue extraction tools for SparkFE
Home-page: https://github.com/4paradigm/SparkFE
Author: 4Paradigm
Author-email: chendihao@4paradigm.com
License: Apache License 2.0
Platform: UNKNOWN
